odoo9_addon_stock_picking_invoice_link-9.0.2.0.0-py2.7-nspkg.pth
odoo9_addon_stock_picking_invoice_link-9.0.2.0.0.dist-info/DESCRIPTION.rst
odoo9_addon_stock_picking_invoice_link-9.0.2.0.0.dist-info/METADATA
odoo9_addon_stock_picking_invoice_link-9.0.2.0.0.dist-info/RECORD
odoo9_addon_stock_picking_invoice_link-9.0.2.0.0.dist-info/WHEEL
odoo9_addon_stock_picking_invoice_link-9.0.2.0.0.dist-info/metadata.json
odoo9_addon_stock_picking_invoice_link-9.0.2.0.0.dist-info/namespace_packages.txt
odoo9_addon_stock_picking_invoice_link-9.0.2.0.0.dist-info/top_level.txt
odoo_addons/stock_picking_invoice_link/README.rst
odoo_addons/stock_picking_invoice_link/__init__.py
odoo_addons/stock_picking_invoice_link/__openerp__.py
odoo_addons/stock_picking_invoice_link/i18n/de.po
odoo_addons/stock_picking_invoice_link/i18n/es.po
odoo_addons/stock_picking_invoice_link/i18n/fi.po
odoo_addons/stock_picking_invoice_link/i18n/fr.po
odoo_addons/stock_picking_invoice_link/i18n/it.po
odoo_addons/stock_picking_invoice_link/i18n/pt_BR.po
odoo_addons/stock_picking_invoice_link/i18n/sl.po
odoo_addons/stock_picking_invoice_link/models/__init__.py
odoo_addons/stock_picking_invoice_link/models/account_invoice.py
odoo_addons/stock_picking_invoice_link/models/sale_order.py
odoo_addons/stock_picking_invoice_link/models/stock_move.py
odoo_addons/stock_picking_invoice_link/models/stock_picking.py
odoo_addons/stock_picking_invoice_link/static/description/icon.png
odoo_addons/stock_picking_invoice_link/tests/__init__.py
odoo_addons/stock_picking_invoice_link/tests/test_stock_picking_invoice_link.py
odoo_addons/stock_picking_invoice_link/views/account_invoice_view.xml
odoo_addons/stock_picking_invoice_link/views/stock_view.xml
