Metadata-Version: 2.0
Name: odoo9-addon-stock-picking-invoice-link
Version: 9.0.2.0.0
Summary: Adds link between pickings and invoices
Home-page: http://www.agilebg.com
Author: Agile Business Group, Tecnativa, BCIM sprl, Odoo Community Association (OCA)
Author-email: support@odoo-community.org
License: AGPL-3
Platform: UNKNOWN
Classifier: Programming Language :: Python :: 2.7
Classifier: Framework :: Odoo
Classifier: License :: OSI Approved :: GNU Affero General Public License v3
Requires-Dist: odoo (<9.1a,>=9.0a)
